{
  "myTestMod:DefaultCommonAttack": {
    "NAME": "Strike",
    "DESCRIPTION": "Deal !D! damage. NL [#0000ff]This[] [#ff0000]Is[] [#ffff00]How[] [#88888]color[] [#ff00ff]works.[]"
  },
  "myTestMod:DefaultCommonSkill": {
    "NAME": "Defend",
    "DESCRIPTION": "Gain !B! Block. NL myTestMod:Multiword_Keyword."
  },
  "myTestMod:DefaultCommonPower": {
    "NAME": "Hold Place",
    "DESCRIPTION": "Gain !M! myTestMod:Keyword.",
    "UPGRADE_DESCRIPTION": "Gain !M! myTestMod:Keywords."
  },
  "myTestMod:DefaultUncommonAttack": {
    "NAME": "Big slap",
    "DESCRIPTION": "Deal !D! damage."
  },
  "myTestMod:DefaultUncommonSkill": {
    "NAME": "A Better Defend",
    "DESCRIPTION": "Gain !B! Plated Armor. Affected by Dexterity."
  },
  "myTestMod:DefaultUncommonPower": {
    "NAME": "Weirdness",
    "DESCRIPTION": "Gain X myTestMod:Keywords.",
    "UPGRADE_DESCRIPTION": "Gain X +1 myTestMod:Keywords."
  },
  "myTestMod:DefaultRareAttack": {
    "NAME": "TOUCH",
    "DESCRIPTION": "Deal !D! damage."
  },
  "myTestMod:DefaultRareSkill": {
    "NAME": "For Each Loop x2",
    "DESCRIPTION": "Apply !M! Vulnerable to all enemies, 2 times.",
    "UPGRADE_DESCRIPTION": "Apply !M! Vulnerable to all enemies, 3 times."
  },
  "myTestMod:DefaultRarePower": {
    "NAME": "In-Progress Form",
    "DESCRIPTION": "At the start of your turn, play a TOUCH."
  },
  "myTestMod:DefaultAttackWithVariable": {
    "NAME": "Special Strike",
    "DESCRIPTION": "Deal !D! damage [E] times. NL (Deal !myTestMod:ENERGY_DAMAGE! damage total.)"
  },
  "myTestMod:DefaultSecondMagicNumberSkill": {
    "NAME": "Cool 2 Number Card",
    "DESCRIPTION": "Apply !M! Vulnerable and !myTestMod:SecondMagic! poison to an enemy."
  },
  "myTestMod:OrbSkill": {
    "NAME": "Get Orb",
    "DESCRIPTION": "Channel 1 Default Orb."
  }
}
